CHANGELOG.rst
LICENSE.txt
MANIFEST.in
README.rst
requirements.txt
setup.py
thonny_exersys.egg-info/PKG-INFO
thonny_exersys.egg-info/SOURCES.txt
thonny_exersys.egg-info/dependency_links.txt
thonny_exersys.egg-info/requires.txt
thonny_exersys.egg-info/top_level.txt
thonnycontrib/exersys.py
thonnycontrib/moodle_vpl.py